MANIFEST.in
README.md
setup.py
gardnr/__init__.py
gardnr/automata.py
gardnr/cli.py
gardnr/constants.py
gardnr/drivers.py
gardnr/grow.py
gardnr/logger.py
gardnr/metrics.py
gardnr/models.py
gardnr/mqtt.py
gardnr/reflection.py
gardnr/server.py
gardnr/settings.py
gardnr.egg-info/PKG-INFO
gardnr.egg-info/SOURCES.txt
gardnr.egg-info/dependency_links.txt
gardnr.egg-info/entry_points.txt
gardnr.egg-info/requires.txt
gardnr.egg-info/top_level.txt
gardnr/static/bootstrap-alert.js
gardnr/static/bootstrap-button.js
gardnr/static/bootstrap-carousel.js
gardnr/static/bootstrap-collapse.js
gardnr/static/bootstrap-dropdown.js
gardnr/static/bootstrap-modal.js
gardnr/static/bootstrap-popover.js
gardnr/static/bootstrap-responsive.css
gardnr/static/bootstrap-scrollspy.js
gardnr/static/bootstrap-tab.js
gardnr/static/bootstrap-tooltip.js
gardnr/static/bootstrap-transition.js
gardnr/static/bootstrap-typeahead.js
gardnr/static/bootstrap.css
gardnr/static/jquery.js
gardnr/static/fonts/Fixedsys500c.woff
gardnr/tasks/__init__.py
gardnr/tasks/power.py
gardnr/tasks/read.py
gardnr/tasks/write.py
gardnr/templates/exporter_driver.py
gardnr/templates/forms.html
gardnr/templates/log_form.html
gardnr/templates/power_driver.py
gardnr/templates/sensor_driver.py
tests/tasks/__init__.py
tests/tasks/test_power.py
tests/tasks/test_read.py
tests/tasks/test_write.py