Metadata-Version: 1.0
Name: gardnr
Version: 0.5.11
Summary: Monitor and control your grow operation.
Home-page: https://github.com/gardnr/gardnr
Author: Jason Biegel
Author-email: UNKNOWN
License: LICENSE
Platform: UNKNOWN
